yyes/__init__.py
yyes/yyes.py
yyes-1.1.1.dist-info/METADATA
yyes-1.1.1.dist-info/WHEEL
yyes-1.1.1.dist-info/top_level.txt
yyes-1.1.1.dist-info/RECORD
